odoo/addons/l10n_fi_business_code/README.rst
odoo/addons/l10n_fi_business_code/__init__.py
odoo/addons/l10n_fi_business_code/__manifest__.py
odoo/addons/l10n_fi_business_code/data/res_partner_id_category.xml
odoo/addons/l10n_fi_business_code/i18n/fi.po
odoo/addons/l10n_fi_business_code/i18n/l10n_fi_business_code.pot
odoo/addons/l10n_fi_business_code/models/__init__.py
odoo/addons/l10n_fi_business_code/models/res_partner.py
odoo/addons/l10n_fi_business_code/static/description/icon.png
odoo/addons/l10n_fi_business_code/views/res_partner.xml
odoo11_addon_l10n_fi_business_code-11.0.1.0.0.99.dev2.dist-info/METADATA
odoo11_addon_l10n_fi_business_code-11.0.1.0.0.99.dev2.dist-info/RECORD
odoo11_addon_l10n_fi_business_code-11.0.1.0.0.99.dev2.dist-info/WHEEL
odoo11_addon_l10n_fi_business_code-11.0.1.0.0.99.dev2.dist-info/top_level.txt
